{
  "version": "7",
  "dialect": "postgresql",
  "entries": [
    {
      "idx": 0,
      "version": "7",
      "when": 1776591514378,
      "tag": "0000_warm_doorman",
      "breakpoints": true
    },
    {
      "idx": 1,
      "version": "7",
      "when": 1776619780710,
      "tag": "0001_loose_gorilla_man",
      "breakpoints": true
    },
    {
      "idx": 2,
      "version": "7",
      "when": 1776964912160,
      "tag": "0002_noisy_excalibur",
      "breakpoints": true
    },
    {
      "idx": 3,
      "version": "7",
      "when": 1777032221953,
      "tag": "0003_warm_preak",
      "breakpoints": true
    },
    {
      "idx": 4,
      "version": "7",
      "when": 1777060636250,
      "tag": "0004_keen_betty_ross",
      "breakpoints": true
    },
    {
      "idx": 5,
      "version": "7",
      "when": 1777154527047,
      "tag": "0005_wild_satana",
      "breakpoints": true
    },
    {
      "idx": 6,
      "version": "7",
      "when": 1777154754443,
      "tag": "0006_salty_gressill",
      "breakpoints": true
    },
    {
      "idx": 7,
      "version": "7",
      "when": 1777159792526,
      "tag": "0007_bored_kulan_gath",
      "breakpoints": true
    },
    {
      "idx": 8,
      "version": "7",
      "when": 1777197706372,
      "tag": "0008_steady_starhawk",
      "breakpoints": true
    },
    {
      "idx": 9,
      "version": "7",
      "when": 1777198453686,
      "tag": "0009_lying_morph",
      "breakpoints": true
    },
    {
      "idx": 10,
      "version": "7",
      "when": 1777215327391,
      "tag": "0010_chemical_pepper_potts",
      "breakpoints": true
    },
    {
      "idx": 11,
      "version": "7",
      "when": 1777216270521,
      "tag": "0011_furry_prima",
      "breakpoints": true
    },
    {
      "idx": 12,
      "version": "7",
      "when": 1777220751549,
      "tag": "0012_clean_scrambler",
      "breakpoints": true
    },
    {
      "idx": 13,
      "version": "7",
      "when": 1777224562633,
      "tag": "0013_strange_loki",
      "breakpoints": true
    },
    {
      "idx": 14,
      "version": "7",
      "when": 1777232794783,
      "tag": "0014_blushing_microbe",
      "breakpoints": true
    },
    {
      "idx": 15,
      "version": "7",
      "when": 1777341213008,
      "tag": "0015_windy_miracleman",
      "breakpoints": true
    },
    {
      "idx": 16,
      "version": "7",
      "when": 1777342682067,
      "tag": "0016_silent_caretaker",
      "breakpoints": true
    },
    {
      "idx": 17,
      "version": "7",
      "when": 1777344433849,
      "tag": "0017_safe_catseye",
      "breakpoints": true
    },
    {
      "idx": 18,
      "version": "7",
      "when": 1777438395541,
      "tag": "0018_abnormal_the_call",
      "breakpoints": true
    },
    {
      "idx": 19,
      "version": "7",
      "when": 1777438437328,
      "tag": "0019_needy_peter_quill",
      "breakpoints": true
    },
    {
      "idx": 20,
      "version": "7",
      "when": 1777438487005,
      "tag": "0020_great_cobalt_man",
      "breakpoints": true
    },
    {
      "idx": 21,
      "version": "7",
      "when": 1777438554688,
      "tag": "0021_vengeful_vengeance",
      "breakpoints": true
    },
    {
      "idx": 22,
      "version": "7",
      "when": 1777438624490,
      "tag": "0022_goofy_gamma_corps",
      "breakpoints": true
    },
    {
      "idx": 23,
      "version": "7",
      "when": 1777438733388,
      "tag": "0023_friendly_doctor_octopus",
      "breakpoints": true
    },
    {
      "idx": 24,
      "version": "7",
      "when": 1777479664414,
      "tag": "0024_lucky_gorilla_man",
      "breakpoints": true
    },
    {
      "idx": 25,
      "version": "7",
      "when": 1777631541042,
      "tag": "0025_cheerful_cerise",
      "breakpoints": true
    }
  ]
}